oss_png_transfer/DataPreProcessor.py
oss_png_transfer/MLPForMINIST.py
oss_png_transfer/PNGProcessor.py
oss_png_transfer/__init__.py
oss_png_transfer-0.1.0.dist-info/LICENCE
oss_png_transfer-0.1.0.dist-info/METADATA
oss_png_transfer-0.1.0.dist-info/WHEEL
oss_png_transfer-0.1.0.dist-info/top_level.txt
oss_png_transfer-0.1.0.dist-info/RECORD
