Metadata-Version: 2.1
Name: oss_png_transfer
Version: 0.1.0
Summary: A package for PNG transfer and processing
Home-page: https://github.com/your_username/oss_png_transfer
Author: 이준명
Author-email: your_email@example.com
Classifier: Programming Language :: Python :: 3
Classifier: License :: OSI Approved :: MIT License
Classifier: Operating System :: OS Independent
Requires-Python: >=3.6
License-File: LICENCE
